{
  "annotations": {
    "list": [
      {
        "builtIn": 1,
        "datasource": {
          "type": "grafana",
          "uid": "-- Grafana --"
        },
        "enable": true,
        "hide": true,
        "iconColor": "rgba(0, 211, 255, 1)",
        "name": "Annotations & Alerts",
        "type": "dashboard"
      }
    ]
  },
  "editable": true,
  "fiscalYearStartMonth": 0,
  "graphTooltip": 1,
  "id": null,
  "links": [],
  "panels": [
    {
      "id": 1,
      "type": "stat",
      "title": "Max Overload Stage",
      "datasource": {
        "type": "prometheus",
        "uid": "prometheus"
      },
      "gridPos": {
        "h": 5,
        "w": 6,
        "x": 0,
        "y": 0
      },
      "targets": [
        {
          "refId": "A",
          "expr": "max(chatapp_overload_stage{job=\"chatapp-api\",vm=~\"$vm\",worker_port=~\"$worker\"}) or vector(0)"
        }
      ],
      "options": {
        "colorMode": "background",
        "graphMode": "none",
        "justifyMode": "center",
        "orientation": "auto",
        "reduceOptions": {
          "calcs": [
            "lastNotNull"
          ],
          "fields": "",
          "values": false
        },
        "textMode": "value"
      },
      "fieldConfig": {
        "defaults": {
          "color": {
            "mode": "thresholds"
          },
          "thresholds": {
            "mode": "absolute",
            "steps": [
              {
                "color": "green",
                "value": null
              },
              {
                "color": "red",
                "value": 0.5
              }
            ]
          },
          "unit": "none"
        },
        "overrides": []
      },
      "description": "Red immediately if any worker enters overload stage > 0."
    },
    {
      "id": 2,
      "type": "stat",
      "title": "5xx Error % (5m)",
      "datasource": {
        "type": "prometheus",
        "uid": "prometheus"
      },
      "gridPos": {
        "h": 5,
        "w": 6,
        "x": 6,
        "y": 0
      },
      "targets": [
        {
          "refId": "A",
          "expr": "100 * sum(increase(http_server_requests_total{job=\"chatapp-api\",vm=~\"$vm\",worker_port=~\"$worker\",status_class=\"5xx\"}[5m])) / clamp_min(sum(increase(http_server_requests_total{job=\"chatapp-api\",vm=~\"$vm\",worker_port=~\"$worker\"}[5m])), 1)"
        }
      ],
      "options": {
        "colorMode": "background",
        "graphMode": "none",
        "justifyMode": "center",
        "orientation": "auto",
        "reduceOptions": {
          "calcs": [
            "lastNotNull"
          ],
          "fields": "",
          "values": false
        },
        "textMode": "value"
      },
      "fieldConfig": {
        "defaults": {
          "color": {
            "mode": "thresholds"
          },
          "thresholds": {
            "mode": "absolute",
            "steps": [
              {
                "color": "green",
                "value": null
              },
              {
                "color": "yellow",
                "value": 0.05
              },
              {
                "color": "red",
                "value": 0.1
              }
            ]
          },
          "unit": "percent",
          "decimals": 3
        },
        "overrides": []
      },
      "description": "5xx percentage over the last 5 minutes. Red above 0.1%."
    },
    {
      "id": 3,
      "type": "stat",
      "title": "POST /messages p95",
      "datasource": {
        "type": "prometheus",
        "uid": "prometheus"
      },
      "gridPos": {
        "h": 5,
        "w": 6,
        "x": 12,
        "y": 0
      },
      "targets": [
        {
          "refId": "A",
          "expr": "histogram_quantile(0.95, sum by (le) (rate(http_server_request_duration_ms_bucket{job=\"chatapp-api\",vm=~\"$vm\",worker_port=~\"$worker\",method=\"POST\",route=~\"/api/v1/messages/?\"}[2m])))"
        }
      ],
      "options": {
        "colorMode": "background",
        "graphMode": "none",
        "justifyMode": "center",
        "orientation": "auto",
        "reduceOptions": {
          "calcs": [
            "lastNotNull"
          ],
          "fields": "",
          "values": false
        },
        "textMode": "value"
      },
      "fieldConfig": {
        "defaults": {
          "color": {
            "mode": "thresholds"
          },
          "thresholds": {
            "mode": "absolute",
            "steps": [
              {
                "color": "green",
                "value": null
              },
              {
                "color": "yellow",
                "value": 250
              },
              {
                "color": "red",
                "value": 500
              }
            ]
          },
          "unit": "ms"
        },
        "overrides": []
      },
      "description": "Current p95 POST /api/v1/messages latency."
    },
    {
      "id": 4,
      "type": "stat",
      "title": "WS Replay Timeout Rate",
      "datasource": {
        "type": "prometheus",
        "uid": "prometheus"
      },
      "gridPos": {
        "h": 5,
        "w": 6,
        "x": 18,
        "y": 0
      },
      "targets": [
        {
          "refId": "A",
          "expr": "sum(rate(ws_replay_query_total{job=\"chatapp-api\",vm=~\"$vm\",worker_port=~\"$worker\",result=\"timeout\"}[2m]))"
        }
      ],
      "options": {
        "colorMode": "background",
        "graphMode": "none",
        "justifyMode": "center",
        "orientation": "auto",
        "reduceOptions": {
          "calcs": [
            "lastNotNull"
          ],
          "fields": "",
          "values": false
        },
        "textMode": "value"
      },
      "fieldConfig": {
        "defaults": {
          "color": {
            "mode": "thresholds"
          },
          "thresholds": {
            "mode": "absolute",
            "steps": [
              {
                "color": "green",
                "value": null
              },
              {
                "color": "red",
                "value": 1e-06
              }
            ]
          },
          "unit": "reqps"
        },
        "overrides": []
      },
      "description": "Any non-zero timeout replay rate should stand out immediately."
    },
    {
      "id": 5,
      "type": "row",
      "title": "Section 1 \u2014 DB Write Contention",
      "gridPos": {
        "h": 1,
        "w": 24,
        "x": 0,
        "y": 5
      },
      "collapsed": false,
      "panels": []
    },
    {
      "id": 6,
      "type": "timeseries",
      "title": "PG Pool Waiting Across Workers",
      "datasource": {
        "type": "prometheus",
        "uid": "prometheus"
      },
      "gridPos": {
        "h": 8,
        "w": 12,
        "x": 0,
        "y": 6
      },
      "targets": [
        {
          "refId": "A",
          "expr": "max by (vm, worker_port) (pg_pool_waiting{job=\"chatapp-api\",vm=~\"$vm\",worker_port=~\"$worker\"})",
          "legendFormat": "{{vm}}:{{worker_port}}"
        },
        {
          "refId": "B",
          "expr": "4",
          "legendFormat": "warn 4"
        },
        {
          "refId": "C",
          "expr": "8",
          "legendFormat": "alert 8"
        }
      ],
      "options": {
        "legend": {
          "displayMode": "list",
          "placement": "bottom",
          "showLegend": true
        },
        "tooltip": {
          "mode": "multi",
          "sort": "desc"
        }
      },
      "fieldConfig": {
        "defaults": {
          "unit": "none",
          "color": {
            "mode": "thresholds"
          },
          "custom": {
            "drawStyle": "line",
            "lineInterpolation": "linear",
            "barAlignment": 0,
            "lineWidth": 2,
            "fillOpacity": 10,
            "gradientMode": "none",
            "spanNulls": false,
            "showPoints": "never",
            "pointSize": 5,
            "stacking": {
              "mode": "none",
              "group": "A"
            },
            "axisPlacement": "auto",
            "axisLabel": "",
            "axisColorMode": "text",
            "scaleDistribution": {
              "type": "linear"
            },
            "axisCenteredZero": false,
            "hideFrom": {
              "tooltip": false,
              "viz": false,
              "legend": false
            },
            "thresholdsStyle": {
              "mode": "line"
            }
          },
          "thresholds": {
            "mode": "absolute",
            "steps": [
              {
                "color": "green",
                "value": null
              },
              {
                "color": "yellow",
                "value": 4
              },
              {
                "color": "red",
                "value": 8
              }
            ]
          }
        },
        "overrides": []
      },
      "description": "Queue depth waiting for PG clients. Alert threshold is 8."
    },
    {
      "id": 7,
      "type": "timeseries",
      "title": "PG Circuit Breaker Reject Rate",
      "datasource": {
        "type": "prometheus",
        "uid": "prometheus"
      },
      "gridPos": {
        "h": 8,
        "w": 12,
        "x": 12,
        "y": 6
      },
      "targets": [
        {
          "refId": "A",
          "expr": "sum by (vm, worker_port) (rate(pg_pool_circuit_breaker_rejects_total{job=\"chatapp-api\",vm=~\"$vm\",worker_port=~\"$worker\"}[2m]))",
          "legendFormat": "{{vm}}:{{worker_port}}"
        }
      ],
      "options": {
        "legend": {
          "displayMode": "list",
          "placement": "bottom",
          "showLegend": true
        },
        "tooltip": {
          "mode": "multi",
          "sort": "desc"
        }
      },
      "fieldConfig": {
        "defaults": {
          "unit": "reqps",
          "color": {
            "mode": "thresholds"
          },
          "custom": {
            "drawStyle": "line",
            "lineInterpolation": "linear",
            "barAlignment": 0,
            "lineWidth": 2,
            "fillOpacity": 10,
            "gradientMode": "none",
            "spanNulls": false,
            "showPoints": "never",
            "pointSize": 5,
            "stacking": {
              "mode": "none",
              "group": "A"
            },
            "axisPlacement": "auto",
            "axisLabel": "",
            "axisColorMode": "text",
            "scaleDistribution": {
              "type": "linear"
            },
            "axisCenteredZero": false,
            "hideFrom": {
              "tooltip": false,
              "viz": false,
              "legend": false
            },
            "thresholdsStyle": {
              "mode": "line"
            }
          },
          "thresholds": {
            "mode": "absolute",
            "steps": [
              {
                "color": "green",
                "value": null
              },
              {
                "color": "yellow",
                "value": 0.01
              },
              {
                "color": "red",
                "value": 0.1
              }
            ]
          }
        },
        "overrides": []
      },
      "description": "Immediate rejects when DB checkout pressure crosses the breaker."
    },
    {
      "id": 8,
      "type": "timeseries",
      "title": "PG Operation Error Rate by Reason",
      "datasource": {
        "type": "prometheus",
        "uid": "prometheus"
      },
      "gridPos": {
        "h": 8,
        "w": 8,
        "x": 0,
        "y": 14
      },
      "targets": [
        {
          "refId": "A",
          "expr": "sum by (reason) (rate(pg_pool_operation_errors_total{job=\"chatapp-api\",vm=~\"$vm\",worker_port=~\"$worker\"}[2m]))",
          "legendFormat": "{{reason}}"
        }
      ],
      "options": {
        "legend": {
          "displayMode": "list",
          "placement": "bottom",
          "showLegend": true
        },
        "tooltip": {
          "mode": "multi",
          "sort": "desc"
        }
      },
      "fieldConfig": {
        "defaults": {
          "unit": "reqps",
          "color": {
            "mode": "thresholds"
          },
          "custom": {
            "drawStyle": "line",
            "lineInterpolation": "linear",
            "barAlignment": 0,
            "lineWidth": 2,
            "fillOpacity": 10,
            "gradientMode": "none",
            "spanNulls": false,
            "showPoints": "never",
            "pointSize": 5,
            "stacking": {
              "mode": "none",
              "group": "A"
            },
            "axisPlacement": "auto",
            "axisLabel": "",
            "axisColorMode": "text",
            "scaleDistribution": {
              "type": "linear"
            },
            "axisCenteredZero": false,
            "hideFrom": {
              "tooltip": false,
              "viz": false,
              "legend": false
            },
            "thresholdsStyle": {
              "mode": "line"
            }
          },
          "thresholds": {
            "mode": "absolute",
            "steps": [
              {
                "color": "green",
                "value": null
              },
              {
                "color": "yellow",
                "value": 0.01
              },
              {
                "color": "red",
                "value": 0.1
              }
            ]
          }
        },
        "overrides": []
      },
      "description": "Especially watch acquire_timeout versus connection/shutdown/other."
    },
    {
      "id": 9,
      "type": "timeseries",
      "title": "POST /messages Responses by Status",
      "datasource": {
        "type": "prometheus",
        "uid": "prometheus"
      },
      "gridPos": {
        "h": 8,
        "w": 8,
        "x": 8,
        "y": 14
      },
      "targets": [
        {
          "refId": "A",
          "expr": "sum by (vm, status_code) (rate(message_post_response_total{job=\"chatapp-api\",vm=~\"$vm\",worker_port=~\"$worker\"}[2m]))",
          "legendFormat": "{{status_code}}"
        }
      ],
      "options": {
        "legend": {
          "displayMode": "list",
          "placement": "bottom",
          "showLegend": true
        },
        "tooltip": {
          "mode": "multi",
          "sort": "desc"
        }
      },
      "fieldConfig": {
        "defaults": {
          "unit": "reqps",
          "color": {
            "mode": "thresholds"
          },
          "custom": {
            "drawStyle": "line",
            "lineInterpolation": "linear",
            "barAlignment": 0,
            "lineWidth": 2,
            "fillOpacity": 10,
            "gradientMode": "none",
            "spanNulls": false,
            "showPoints": "never",
            "pointSize": 5,
            "stacking": {
              "mode": "normal",
              "group": "A"
            },
            "axisPlacement": "auto",
            "axisLabel": "",
            "axisColorMode": "text",
            "scaleDistribution": {
              "type": "linear"
            },
            "axisCenteredZero": false,
            "hideFrom": {
              "tooltip": false,
              "viz": false,
              "legend": false
            },
            "thresholdsStyle": {
              "mode": "line"
            }
          },
          "thresholds": {
            "mode": "absolute",
            "steps": [
              {
                "color": "green",
                "value": null
              },
              {
                "color": "yellow",
                "value": 1
              },
              {
                "color": "red",
                "value": 5
              }
            ]
          }
        },
        "overrides": [
          {
            "matcher": {
              "id": "byName",
              "options": "201"
            },
            "properties": [
              {
                "id": "color",
                "value": {
                  "mode": "fixed",
                  "fixedColor": "green"
                }
              }
            ]
          },
          {
            "matcher": {
              "id": "byName",
              "options": "503"
            },
            "properties": [
              {
                "id": "color",
                "value": {
                  "mode": "fixed",
                  "fixedColor": "red"
                }
              }
            ]
          },
          {
            "matcher": {
              "id": "byRegexp",
              "options": "5.."
            },
            "properties": [
              {
                "id": "color",
                "value": {
                  "mode": "fixed",
                  "fixedColor": "red"
                }
              }
            ]
          },
          {
            "matcher": {
              "id": "byRegexp",
              "options": "4.."
            },
            "properties": [
              {
                "id": "color",
                "value": {
                  "mode": "fixed",
                  "fixedColor": "yellow"
                }
              }
            ]
          }
        ]
      },
      "description": "Stacked rate of POST /api/v1/messages responses. 503 spikes should be obvious."
    },
    {
      "id": 10,
      "type": "timeseries",
      "title": "POST /messages Latency p95 / p99",
      "datasource": {
        "type": "prometheus",
        "uid": "prometheus"
      },
      "gridPos": {
        "h": 8,
        "w": 8,
        "x": 16,
        "y": 14
      },
      "targets": [
        {
          "refId": "A",
          "expr": "histogram_quantile(0.95, sum by (le) (rate(http_server_request_duration_ms_bucket{job=\"chatapp-api\",vm=~\"$vm\",worker_port=~\"$worker\",method=\"POST\",route=~\"/api/v1/messages/?\"}[2m])))",
          "legendFormat": "p95"
        },
        {
          "refId": "B",
          "expr": "histogram_quantile(0.99, sum by (le) (rate(http_server_request_duration_ms_bucket{job=\"chatapp-api\",vm=~\"$vm\",worker_port=~\"$worker\",method=\"POST\",route=~\"/api/v1/messages/?\"}[2m])))",
          "legendFormat": "p99"
        },
        {
          "refId": "C",
          "expr": "250",
          "legendFormat": "warn 250ms"
        },
        {
          "refId": "D",
          "expr": "500",
          "legendFormat": "critical 500ms"
        }
      ],
      "options": {
        "legend": {
          "displayMode": "list",
          "placement": "bottom",
          "showLegend": true
        },
        "tooltip": {
          "mode": "multi",
          "sort": "desc"
        }
      },
      "fieldConfig": {
        "defaults": {
          "unit": "ms",
          "color": {
            "mode": "thresholds"
          },
          "custom": {
            "drawStyle": "line",
            "lineInterpolation": "linear",
            "barAlignment": 0,
            "lineWidth": 2,
            "fillOpacity": 10,
            "gradientMode": "none",
            "spanNulls": false,
            "showPoints": "never",
            "pointSize": 5,
            "stacking": {
              "mode": "none",
              "group": "A"
            },
            "axisPlacement": "auto",
            "axisLabel": "",
            "axisColorMode": "text",
            "scaleDistribution": {
              "type": "linear"
            },
            "axisCenteredZero": false,
            "hideFrom": {
              "tooltip": false,
              "viz": false,
              "legend": false
            },
            "thresholdsStyle": {
              "mode": "line"
            }
          },
          "thresholds": {
            "mode": "absolute",
            "steps": [
              {
                "color": "green",
                "value": null
              },
              {
                "color": "yellow",
                "value": 250
              },
              {
                "color": "red",
                "value": 500
              }
            ]
          }
        },
        "overrides": []
      },
      "description": "Histogram p95/p99 specifically for POST /api/v1/messages."
    },
    {
      "id": 11,
      "type": "timeseries",
      "title": "Overload Stage per Worker",
      "datasource": {
        "type": "prometheus",
        "uid": "prometheus"
      },
      "gridPos": {
        "h": 8,
        "w": 24,
        "x": 0,
        "y": 22
      },
      "targets": [
        {
          "refId": "A",
          "expr": "max by (vm, worker_port) (chatapp_overload_stage{job=\"chatapp-api\",vm=~\"$vm\",worker_port=~\"$worker\"})",
          "legendFormat": "{{vm}}:{{worker_port}}"
        }
      ],
      "options": {
        "legend": {
          "displayMode": "list",
          "placement": "bottom",
          "showLegend": true
        },
        "tooltip": {
          "mode": "multi",
          "sort": "desc"
        }
      },
      "fieldConfig": {
        "defaults": {
          "unit": "none",
          "color": {
            "mode": "thresholds"
          },
          "custom": {
            "drawStyle": "line",
            "lineInterpolation": "linear",
            "barAlignment": 0,
            "lineWidth": 2,
            "fillOpacity": 10,
            "gradientMode": "none",
            "spanNulls": false,
            "showPoints": "never",
            "pointSize": 5,
            "stacking": {
              "mode": "none",
              "group": "A"
            },
            "axisPlacement": "auto",
            "axisLabel": "",
            "axisColorMode": "text",
            "scaleDistribution": {
              "type": "linear"
            },
            "axisCenteredZero": false,
            "hideFrom": {
              "tooltip": false,
              "viz": false,
              "legend": false
            },
            "thresholdsStyle": {
              "mode": "line"
            }
          },
          "thresholds": {
            "mode": "absolute",
            "steps": [
              {
                "color": "green",
                "value": null
              },
              {
                "color": "yellow",
                "value": 1
              },
              {
                "color": "red",
                "value": 2
              }
            ]
          }
        },
        "overrides": []
      },
      "description": "Shows load-shedding stage per app worker."
    },
    {
      "id": 12,
      "type": "row",
      "title": "Section 2 \u2014 WebSocket Delivery Health",
      "gridPos": {
        "h": 1,
        "w": 24,
        "x": 0,
        "y": 30
      },
      "collapsed": false,
      "panels": []
    },
    {
      "id": 13,
      "type": "timeseries",
      "title": "WS Replay Query Rate by Result",
      "datasource": {
        "type": "prometheus",
        "uid": "prometheus"
      },
      "gridPos": {
        "h": 8,
        "w": 12,
        "x": 0,
        "y": 31
      },
      "targets": [
        {
          "refId": "A",
          "expr": "sum by (result) (rate(ws_replay_query_total{job=\"chatapp-api\",vm=~\"$vm\",worker_port=~\"$worker\"}[2m]))",
          "legendFormat": "{{result}}"
        }
      ],
      "options": {
        "legend": {
          "displayMode": "list",
          "placement": "bottom",
          "showLegend": true
        },
        "tooltip": {
          "mode": "multi",
          "sort": "desc"
        }
      },
      "fieldConfig": {
        "defaults": {
          "unit": "reqps",
          "color": {
            "mode": "thresholds"
          },
          "custom": {
            "drawStyle": "line",
            "lineInterpolation": "linear",
            "barAlignment": 0,
            "lineWidth": 2,
            "fillOpacity": 10,
            "gradientMode": "none",
            "spanNulls": false,
            "showPoints": "never",
            "pointSize": 5,
            "stacking": {
              "mode": "none",
              "group": "A"
            },
            "axisPlacement": "auto",
            "axisLabel": "",
            "axisColorMode": "text",
            "scaleDistribution": {
              "type": "linear"
            },
            "axisCenteredZero": false,
            "hideFrom": {
              "tooltip": false,
              "viz": false,
              "legend": false
            },
            "thresholdsStyle": {
              "mode": "line"
            }
          },
          "thresholds": {
            "mode": "absolute",
            "steps": [
              {
                "color": "green",
                "value": null
              },
              {
                "color": "yellow",
                "value": 0.01
              },
              {
                "color": "red",
                "value": 0.1
              }
            ]
          }
        },
        "overrides": [
          {
            "matcher": {
              "id": "byName",
              "options": "timeout"
            },
            "properties": [
              {
                "id": "color",
                "value": {
                  "mode": "fixed",
                  "fixedColor": "red"
                }
              }
            ]
          },
          {
            "matcher": {
              "id": "byName",
              "options": "ok"
            },
            "properties": [
              {
                "id": "color",
                "value": {
                  "mode": "fixed",
                  "fixedColor": "green"
                }
              }
            ]
          }
        ]
      },
      "description": "Reconnect replay outcomes, especially timeout versus ok."
    },
    {
      "id": 14,
      "type": "timeseries",
      "title": "WS Outbound Queue Block Waits",
      "datasource": {
        "type": "prometheus",
        "uid": "prometheus"
      },
      "gridPos": {
        "h": 8,
        "w": 6,
        "x": 12,
        "y": 31
      },
      "targets": [
        {
          "refId": "A",
          "expr": "sum by (vm, worker_port) (rate(ws_outbound_queue_block_waits_total{job=\"chatapp-api\",vm=~\"$vm\",worker_port=~\"$worker\"}[2m]))",
          "legendFormat": "{{vm}}:{{worker_port}}"
        }
      ],
      "options": {
        "legend": {
          "displayMode": "list",
          "placement": "bottom",
          "showLegend": true
        },
        "tooltip": {
          "mode": "multi",
          "sort": "desc"
        }
      },
      "fieldConfig": {
        "defaults": {
          "unit": "reqps",
          "color": {
            "mode": "thresholds"
          },
          "custom": {
            "drawStyle": "line",
            "lineInterpolation": "linear",
            "barAlignment": 0,
            "lineWidth": 2,
            "fillOpacity": 10,
            "gradientMode": "none",
            "spanNulls": false,
            "showPoints": "never",
            "pointSize": 5,
            "stacking": {
              "mode": "none",
              "group": "A"
            },
            "axisPlacement": "auto",
            "axisLabel": "",
            "axisColorMode": "text",
            "scaleDistribution": {
              "type": "linear"
            },
            "axisCenteredZero": false,
            "hideFrom": {
              "tooltip": false,
              "viz": false,
              "legend": false
            },
            "thresholdsStyle": {
              "mode": "line"
            }
          },
          "thresholds": {
            "mode": "absolute",
            "steps": [
              {
                "color": "green",
                "value": null
              },
              {
                "color": "yellow",
                "value": 0.1
              },
              {
                "color": "red",
                "value": 1
              }
            ]
          }
        },
        "overrides": []
      },
      "description": "Times message-priority enqueues had to wait for bounded queue capacity."
    },
    {
      "id": 15,
      "type": "timeseries",
      "title": "WS Backpressure Events by Action",
      "datasource": {
        "type": "prometheus",
        "uid": "prometheus"
      },
      "gridPos": {
        "h": 8,
        "w": 6,
        "x": 18,
        "y": 31
      },
      "targets": [
        {
          "refId": "A",
          "expr": "sum by (action) (rate(ws_backpressure_events_total{job=\"chatapp-api\",vm=~\"$vm\",worker_port=~\"$worker\"}[2m]))",
          "legendFormat": "{{action}}"
        }
      ],
      "options": {
        "legend": {
          "displayMode": "list",
          "placement": "bottom",
          "showLegend": true
        },
        "tooltip": {
          "mode": "multi",
          "sort": "desc"
        }
      },
      "fieldConfig": {
        "defaults": {
          "unit": "reqps",
          "color": {
            "mode": "thresholds"
          },
          "custom": {
            "drawStyle": "line",
            "lineInterpolation": "linear",
            "barAlignment": 0,
            "lineWidth": 2,
            "fillOpacity": 10,
            "gradientMode": "none",
            "spanNulls": false,
            "showPoints": "never",
            "pointSize": 5,
            "stacking": {
              "mode": "none",
              "group": "A"
            },
            "axisPlacement": "auto",
            "axisLabel": "",
            "axisColorMode": "text",
            "scaleDistribution": {
              "type": "linear"
            },
            "axisCenteredZero": false,
            "hideFrom": {
              "tooltip": false,
              "viz": false,
              "legend": false
            },
            "thresholdsStyle": {
              "mode": "line"
            }
          },
          "thresholds": {
            "mode": "absolute",
            "steps": [
              {
                "color": "green",
                "value": null
              },
              {
                "color": "yellow",
                "value": 0.01
              },
              {
                "color": "red",
                "value": 0.1
              }
            ]
          }
        },
        "overrides": [
          {
            "matcher": {
              "id": "byName",
              "options": "drop"
            },
            "properties": [
              {
                "id": "color",
                "value": {
                  "mode": "fixed",
                  "fixedColor": "yellow"
                }
              }
            ]
          },
          {
            "matcher": {
              "id": "byName",
              "options": "kill"
            },
            "properties": [
              {
                "id": "color",
                "value": {
                  "mode": "fixed",
                  "fixedColor": "red"
                }
              }
            ]
          }
        ]
      },
      "description": "Dropped vs killed sockets due to WS send backpressure."
    },
    {
      "id": 16,
      "type": "timeseries",
      "title": "WS Disconnect Rate by Close Code",
      "datasource": {
        "type": "prometheus",
        "uid": "prometheus"
      },
      "gridPos": {
        "h": 8,
        "w": 12,
        "x": 0,
        "y": 39
      },
      "targets": [
        {
          "refId": "A",
          "expr": "sum by (code) (rate(ws_disconnects_total{job=\"chatapp-api\",vm=~\"$vm\",worker_port=~\"$worker\"}[2m]))",
          "legendFormat": "code {{code}}"
        }
      ],
      "options": {
        "legend": {
          "displayMode": "list",
          "placement": "bottom",
          "showLegend": true
        },
        "tooltip": {
          "mode": "multi",
          "sort": "desc"
        }
      },
      "fieldConfig": {
        "defaults": {
          "unit": "reqps",
          "color": {
            "mode": "thresholds"
          },
          "custom": {
            "drawStyle": "line",
            "lineInterpolation": "linear",
            "barAlignment": 0,
            "lineWidth": 2,
            "fillOpacity": 10,
            "gradientMode": "none",
            "spanNulls": false,
            "showPoints": "never",
            "pointSize": 5,
            "stacking": {
              "mode": "none",
              "group": "A"
            },
            "axisPlacement": "auto",
            "axisLabel": "",
            "axisColorMode": "text",
            "scaleDistribution": {
              "type": "linear"
            },
            "axisCenteredZero": false,
            "hideFrom": {
              "tooltip": false,
              "viz": false,
              "legend": false
            },
            "thresholdsStyle": {
              "mode": "line"
            }
          },
          "thresholds": {
            "mode": "absolute",
            "steps": [
              {
                "color": "green",
                "value": null
              },
              {
                "color": "yellow",
                "value": 0.05
              },
              {
                "color": "red",
                "value": 0.2
              }
            ]
          }
        },
        "overrides": [
          {
            "matcher": {
              "id": "byName",
              "options": "code 1006"
            },
            "properties": [
              {
                "id": "color",
                "value": {
                  "mode": "fixed",
                  "fixedColor": "red"
                }
              }
            ]
          }
        ]
      },
      "description": "Abnormal disconnects (1006) should stand out."
    },
    {
      "id": 17,
      "type": "timeseries",
      "title": "WS Reconnect Rate by Window",
      "datasource": {
        "type": "prometheus",
        "uid": "prometheus"
      },
      "gridPos": {
        "h": 8,
        "w": 6,
        "x": 12,
        "y": 39
      },
      "targets": [
        {
          "refId": "A",
          "expr": "sum by (window) (rate(ws_reconnects_total{job=\"chatapp-api\",vm=~\"$vm\",worker_port=~\"$worker\"}[2m]))",
          "legendFormat": "{{window}}"
        }
      ],
      "options": {
        "legend": {
          "displayMode": "list",
          "placement": "bottom",
          "showLegend": true
        },
        "tooltip": {
          "mode": "multi",
          "sort": "desc"
        }
      },
      "fieldConfig": {
        "defaults": {
          "unit": "reqps",
          "color": {
            "mode": "thresholds"
          },
          "custom": {
            "drawStyle": "line",
            "lineInterpolation": "linear",
            "barAlignment": 0,
            "lineWidth": 2,
            "fillOpacity": 10,
            "gradientMode": "none",
            "spanNulls": false,
            "showPoints": "never",
            "pointSize": 5,
            "stacking": {
              "mode": "none",
              "group": "A"
            },
            "axisPlacement": "auto",
            "axisLabel": "",
            "axisColorMode": "text",
            "scaleDistribution": {
              "type": "linear"
            },
            "axisCenteredZero": false,
            "hideFrom": {
              "tooltip": false,
              "viz": false,
              "legend": false
            },
            "thresholdsStyle": {
              "mode": "line"
            }
          },
          "thresholds": {
            "mode": "absolute",
            "steps": [
              {
                "color": "green",
                "value": null
              },
              {
                "color": "yellow",
                "value": 0.1
              },
              {
                "color": "red",
                "value": 1
              }
            ]
          }
        },
        "overrides": []
      },
      "description": "Reconnects bucketed by reconnect gap window."
    },
    {
      "id": 18,
      "type": "timeseries",
      "title": "Fanout Publish p95 by Path/Stage",
      "datasource": {
        "type": "prometheus",
        "uid": "prometheus"
      },
      "gridPos": {
        "h": 8,
        "w": 6,
        "x": 18,
        "y": 39
      },
      "targets": [
        {
          "refId": "A",
          "expr": "histogram_quantile(0.95, sum by (le, path, stage) (rate(fanout_publish_duration_ms_bucket{job=\"chatapp-api\",vm=~\"$vm\",worker_port=~\"$worker\"}[2m])))",
          "legendFormat": "{{path}} / {{stage}}"
        }
      ],
      "options": {
        "legend": {
          "displayMode": "list",
          "placement": "bottom",
          "showLegend": true
        },
        "tooltip": {
          "mode": "multi",
          "sort": "desc"
        }
      },
      "fieldConfig": {
        "defaults": {
          "unit": "ms",
          "color": {
            "mode": "thresholds"
          },
          "custom": {
            "drawStyle": "line",
            "lineInterpolation": "linear",
            "barAlignment": 0,
            "lineWidth": 2,
            "fillOpacity": 10,
            "gradientMode": "none",
            "spanNulls": false,
            "showPoints": "never",
            "pointSize": 5,
            "stacking": {
              "mode": "none",
              "group": "A"
            },
            "axisPlacement": "auto",
            "axisLabel": "",
            "axisColorMode": "text",
            "scaleDistribution": {
              "type": "linear"
            },
            "axisCenteredZero": false,
            "hideFrom": {
              "tooltip": false,
              "viz": false,
              "legend": false
            },
            "thresholdsStyle": {
              "mode": "line"
            }
          },
          "thresholds": {
            "mode": "absolute",
            "steps": [
              {
                "color": "green",
                "value": null
              },
              {
                "color": "yellow",
                "value": 100
              },
              {
                "color": "red",
                "value": 250
              }
            ]
          }
        },
        "overrides": []
      },
      "description": "Global fanout stage latency, useful for spotting conversation_dm publish slowdowns."
    },
    {
      "id": 19,
      "type": "row",
      "title": "Section 3 \u2014 Fanout Cache Health",
      "gridPos": {
        "h": 1,
        "w": 24,
        "x": 0,
        "y": 47
      },
      "collapsed": false,
      "panels": []
    },
    {
      "id": 20,
      "type": "timeseries",
      "title": "Fanout Target Cache Rate",
      "datasource": {
        "type": "prometheus",
        "uid": "prometheus"
      },
      "gridPos": {
        "h": 8,
        "w": 12,
        "x": 0,
        "y": 48
      },
      "targets": [
        {
          "refId": "A",
          "expr": "sum by (path, result) (rate(fanout_target_cache_total{job=\"chatapp-api\",vm=~\"$vm\",worker_port=~\"$worker\"}[2m]))",
          "legendFormat": "{{path}} / {{result}}"
        }
      ],
      "options": {
        "legend": {
          "displayMode": "list",
          "placement": "bottom",
          "showLegend": true
        },
        "tooltip": {
          "mode": "multi",
          "sort": "desc"
        }
      },
      "fieldConfig": {
        "defaults": {
          "unit": "reqps",
          "color": {
            "mode": "thresholds"
          },
          "custom": {
            "drawStyle": "line",
            "lineInterpolation": "linear",
            "barAlignment": 0,
            "lineWidth": 2,
            "fillOpacity": 10,
            "gradientMode": "none",
            "spanNulls": false,
            "showPoints": "never",
            "pointSize": 5,
            "stacking": {
              "mode": "none",
              "group": "A"
            },
            "axisPlacement": "auto",
            "axisLabel": "",
            "axisColorMode": "text",
            "scaleDistribution": {
              "type": "linear"
            },
            "axisCenteredZero": false,
            "hideFrom": {
              "tooltip": false,
              "viz": false,
              "legend": false
            },
            "thresholdsStyle": {
              "mode": "line"
            }
          },
          "thresholds": {
            "mode": "absolute",
            "steps": [
              {
                "color": "green",
                "value": null
              },
              {
                "color": "yellow",
                "value": 1
              },
              {
                "color": "red",
                "value": 5
              }
            ]
          }
        },
        "overrides": []
      },
      "description": "Hit/miss/coalesced outcomes for realtime fanout target caches."
    },
    {
      "id": 21,
      "type": "timeseries",
      "title": "Endpoint List Cache Rate",
      "datasource": {
        "type": "prometheus",
        "uid": "prometheus"
      },
      "gridPos": {
        "h": 8,
        "w": 12,
        "x": 12,
        "y": 48
      },
      "targets": [
        {
          "refId": "A",
          "expr": "sum by (endpoint, result) (rate(endpoint_list_cache_total{job=\"chatapp-api\",vm=~\"$vm\",worker_port=~\"$worker\"}[2m]))",
          "legendFormat": "{{endpoint}} / {{result}}"
        }
      ],
      "options": {
        "legend": {
          "displayMode": "list",
          "placement": "bottom",
          "showLegend": true
        },
        "tooltip": {
          "mode": "multi",
          "sort": "desc"
        }
      },
      "fieldConfig": {
        "defaults": {
          "unit": "reqps",
          "color": {
            "mode": "thresholds"
          },
          "custom": {
            "drawStyle": "line",
            "lineInterpolation": "linear",
            "barAlignment": 0,
            "lineWidth": 2,
            "fillOpacity": 10,
            "gradientMode": "none",
            "spanNulls": false,
            "showPoints": "never",
            "pointSize": 5,
            "stacking": {
              "mode": "none",
              "group": "A"
            },
            "axisPlacement": "auto",
            "axisLabel": "",
            "axisColorMode": "text",
            "scaleDistribution": {
              "type": "linear"
            },
            "axisCenteredZero": false,
            "hideFrom": {
              "tooltip": false,
              "viz": false,
              "legend": false
            },
            "thresholdsStyle": {
              "mode": "line"
            }
          },
          "thresholds": {
            "mode": "absolute",
            "steps": [
              {
                "color": "green",
                "value": null
              },
              {
                "color": "yellow",
                "value": 1
              },
              {
                "color": "red",
                "value": 5
              }
            ]
          }
        },
        "overrides": []
      },
      "description": "Cache outcomes for communities/channels/messages/conversations list endpoints."
    },
    {
      "id": 22,
      "type": "timeseries",
      "title": "Conversation Fanout Cache Version Retry Rate",
      "datasource": {
        "type": "prometheus",
        "uid": "prometheus"
      },
      "gridPos": {
        "h": 8,
        "w": 8,
        "x": 0,
        "y": 56
      },
      "targets": [
        {
          "refId": "A",
          "expr": "sum by (outcome) (rate(conversation_fanout_targets_cache_version_retry_total{job=\"chatapp-api\",vm=~\"$vm\",worker_port=~\"$worker\"}[2m]))",
          "legendFormat": "{{outcome}}"
        }
      ],
      "options": {
        "legend": {
          "displayMode": "list",
          "placement": "bottom",
          "showLegend": true
        },
        "tooltip": {
          "mode": "multi",
          "sort": "desc"
        }
      },
      "fieldConfig": {
        "defaults": {
          "unit": "reqps",
          "color": {
            "mode": "thresholds"
          },
          "custom": {
            "drawStyle": "line",
            "lineInterpolation": "linear",
            "barAlignment": 0,
            "lineWidth": 2,
            "fillOpacity": 10,
            "gradientMode": "none",
            "spanNulls": false,
            "showPoints": "never",
            "pointSize": 5,
            "stacking": {
              "mode": "none",
              "group": "A"
            },
            "axisPlacement": "auto",
            "axisLabel": "",
            "axisColorMode": "text",
            "scaleDistribution": {
              "type": "linear"
            },
            "axisCenteredZero": false,
            "hideFrom": {
              "tooltip": false,
              "viz": false,
              "legend": false
            },
            "thresholdsStyle": {
              "mode": "line"
            }
          },
          "thresholds": {
            "mode": "absolute",
            "steps": [
              {
                "color": "green",
                "value": null
              },
              {
                "color": "yellow",
                "value": 0.01
              },
              {
                "color": "red",
                "value": 0.1
              }
            ]
          }
        },
        "overrides": []
      },
      "description": "Retry and uncached_return indicate cache version races under load."
    },
    {
      "id": 23,
      "type": "timeseries",
      "title": "conversation_dm Fanout Publish p95 by Stage",
      "datasource": {
        "type": "prometheus",
        "uid": "prometheus"
      },
      "gridPos": {
        "h": 8,
        "w": 8,
        "x": 8,
        "y": 56
      },
      "targets": [
        {
          "refId": "A",
          "expr": "histogram_quantile(0.95, sum by (le, stage) (rate(fanout_publish_duration_ms_bucket{job=\"chatapp-api\",vm=~\"$vm\",worker_port=~\"$worker\",path=\"conversation_dm\"}[2m])))",
          "legendFormat": "{{stage}} p95"
        }
      ],
      "options": {
        "legend": {
          "displayMode": "list",
          "placement": "bottom",
          "showLegend": true
        },
        "tooltip": {
          "mode": "multi",
          "sort": "desc"
        }
      },
      "fieldConfig": {
        "defaults": {
          "unit": "ms",
          "color": {
            "mode": "thresholds"
          },
          "custom": {
            "drawStyle": "line",
            "lineInterpolation": "linear",
            "barAlignment": 0,
            "lineWidth": 2,
            "fillOpacity": 10,
            "gradientMode": "none",
            "spanNulls": false,
            "showPoints": "never",
            "pointSize": 5,
            "stacking": {
              "mode": "none",
              "group": "A"
            },
            "axisPlacement": "auto",
            "axisLabel": "",
            "axisColorMode": "text",
            "scaleDistribution": {
              "type": "linear"
            },
            "axisCenteredZero": false,
            "hideFrom": {
              "tooltip": false,
              "viz": false,
              "legend": false
            },
            "thresholdsStyle": {
              "mode": "line"
            }
          },
          "thresholds": {
            "mode": "absolute",
            "steps": [
              {
                "color": "green",
                "value": null
              },
              {
                "color": "yellow",
                "value": 50
              },
              {
                "color": "red",
                "value": 150
              }
            ]
          }
        },
        "overrides": []
      },
      "description": "p95 for each conversation_dm fanout stage."
    },
    {
      "id": 24,
      "type": "timeseries",
      "title": "conversation_dm Fanout Publish p99 by Stage",
      "datasource": {
        "type": "prometheus",
        "uid": "prometheus"
      },
      "gridPos": {
        "h": 8,
        "w": 8,
        "x": 16,
        "y": 56
      },
      "targets": [
        {
          "refId": "A",
          "expr": "histogram_quantile(0.99, sum by (le, stage) (rate(fanout_publish_duration_ms_bucket{job=\"chatapp-api\",vm=~\"$vm\",worker_port=~\"$worker\",path=\"conversation_dm\"}[2m])))",
          "legendFormat": "{{stage}} p99"
        }
      ],
      "options": {
        "legend": {
          "displayMode": "list",
          "placement": "bottom",
          "showLegend": true
        },
        "tooltip": {
          "mode": "multi",
          "sort": "desc"
        }
      },
      "fieldConfig": {
        "defaults": {
          "unit": "ms",
          "color": {
            "mode": "thresholds"
          },
          "custom": {
            "drawStyle": "line",
            "lineInterpolation": "linear",
            "barAlignment": 0,
            "lineWidth": 2,
            "fillOpacity": 10,
            "gradientMode": "none",
            "spanNulls": false,
            "showPoints": "never",
            "pointSize": 5,
            "stacking": {
              "mode": "none",
              "group": "A"
            },
            "axisPlacement": "auto",
            "axisLabel": "",
            "axisColorMode": "text",
            "scaleDistribution": {
              "type": "linear"
            },
            "axisCenteredZero": false,
            "hideFrom": {
              "tooltip": false,
              "viz": false,
              "legend": false
            },
            "thresholdsStyle": {
              "mode": "line"
            }
          },
          "thresholds": {
            "mode": "absolute",
            "steps": [
              {
                "color": "green",
                "value": null
              },
              {
                "color": "yellow",
                "value": 100
              },
              {
                "color": "red",
                "value": 250
              }
            ]
          }
        },
        "overrides": []
      },
      "description": "p99 for each conversation_dm fanout stage."
    },
    {
      "id": 25,
      "type": "row",
      "title": "Section 4 \u2014 System Health",
      "gridPos": {
        "h": 1,
        "w": 24,
        "x": 0,
        "y": 64
      },
      "collapsed": false,
      "panels": []
    },
    {
      "id": 26,
      "type": "timeseries",
      "title": "Event Loop Lag p99 per Worker",
      "datasource": {
        "type": "prometheus",
        "uid": "prometheus"
      },
      "gridPos": {
        "h": 8,
        "w": 8,
        "x": 0,
        "y": 65
      },
      "targets": [
        {
          "refId": "A",
          "expr": "1000 * max by (vm, worker_port) (nodejs_eventloop_lag_p99_seconds{job=\"chatapp-api\",vm=~\"$vm\",worker_port=~\"$worker\"})",
          "legendFormat": "{{vm}}:{{worker_port}}"
        },
        {
          "refId": "B",
          "expr": "20",
          "legendFormat": "warn 20ms"
        },
        {
          "refId": "C",
          "expr": "40",
          "legendFormat": "alert 40ms"
        }
      ],
      "options": {
        "legend": {
          "displayMode": "list",
          "placement": "bottom",
          "showLegend": true
        },
        "tooltip": {
          "mode": "multi",
          "sort": "desc"
        }
      },
      "fieldConfig": {
        "defaults": {
          "unit": "ms",
          "color": {
            "mode": "thresholds"
          },
          "custom": {
            "drawStyle": "line",
            "lineInterpolation": "linear",
            "barAlignment": 0,
            "lineWidth": 2,
            "fillOpacity": 10,
            "gradientMode": "none",
            "spanNulls": false,
            "showPoints": "never",
            "pointSize": 5,
            "stacking": {
              "mode": "none",
              "group": "A"
            },
            "axisPlacement": "auto",
            "axisLabel": "",
            "axisColorMode": "text",
            "scaleDistribution": {
              "type": "linear"
            },
            "axisCenteredZero": false,
            "hideFrom": {
              "tooltip": false,
              "viz": false,
              "legend": false
            },
            "thresholdsStyle": {
              "mode": "line"
            }
          },
          "thresholds": {
            "mode": "absolute",
            "steps": [
              {
                "color": "green",
                "value": null
              },
              {
                "color": "orange",
                "value": 120
              },
              {
                "color": "red",
                "value": 250
              }
            ]
          }
        },
        "overrides": []
      },
      "description": "Default prom-client event loop p99 metric per worker."
    },
    {
      "id": 27,
      "type": "timeseries",
      "title": "RSS Memory per Worker",
      "datasource": {
        "type": "prometheus",
        "uid": "prometheus"
      },
      "gridPos": {
        "h": 8,
        "w": 8,
        "x": 8,
        "y": 65
      },
      "targets": [
        {
          "refId": "A",
          "expr": "max by (vm, worker_port) (process_resident_memory_bytes{job=\"chatapp-api\",vm=~\"$vm\",worker_port=~\"$worker\"}) / 1024 / 1024",
          "legendFormat": "{{vm}}:{{worker_port}}"
        },
        {
          "refId": "B",
          "expr": "350",
          "legendFormat": "warn 350MB"
        },
        {
          "refId": "C",
          "expr": "500",
          "legendFormat": "alert 500MB"
        }
      ],
      "options": {
        "legend": {
          "displayMode": "list",
          "placement": "bottom",
          "showLegend": true
        },
        "tooltip": {
          "mode": "multi",
          "sort": "desc"
        }
      },
      "fieldConfig": {
        "defaults": {
          "unit": "decmbytes",
          "color": {
            "mode": "thresholds"
          },
          "custom": {
            "drawStyle": "line",
            "lineInterpolation": "linear",
            "barAlignment": 0,
            "lineWidth": 2,
            "fillOpacity": 10,
            "gradientMode": "none",
            "spanNulls": false,
            "showPoints": "never",
            "pointSize": 5,
            "stacking": {
              "mode": "none",
              "group": "A"
            },
            "axisPlacement": "auto",
            "axisLabel": "",
            "axisColorMode": "text",
            "scaleDistribution": {
              "type": "linear"
            },
            "axisCenteredZero": false,
            "hideFrom": {
              "tooltip": false,
              "viz": false,
              "legend": false
            },
            "thresholdsStyle": {
              "mode": "line"
            }
          },
          "thresholds": {
            "mode": "absolute",
            "steps": [
              {
                "color": "green",
                "value": null
              },
              {
                "color": "orange",
                "value": 650
              },
              {
                "color": "red",
                "value": 800
              }
            ]
          }
        },
        "overrides": []
      },
      "description": "Resident memory per worker against a 500MB threshold."
    },
    {
      "id": 28,
      "type": "timeseries",
      "title": "HTTP Request Rate vs Aborted Rate",
      "datasource": {
        "type": "prometheus",
        "uid": "prometheus"
      },
      "gridPos": {
        "h": 8,
        "w": 8,
        "x": 16,
        "y": 65
      },
      "targets": [
        {
          "refId": "A",
          "expr": "sum(rate(http_server_requests_total{job=\"chatapp-api\",vm=~\"$vm\",worker_port=~\"$worker\"}[2m]))",
          "legendFormat": "completed"
        },
        {
          "refId": "B",
          "expr": "sum(rate(http_server_requests_aborted_total{job=\"chatapp-api\",vm=~\"$vm\",worker_port=~\"$worker\"}[2m]))",
          "legendFormat": "aborted"
        }
      ],
      "options": {
        "legend": {
          "displayMode": "list",
          "placement": "bottom",
          "showLegend": true
        },
        "tooltip": {
          "mode": "multi",
          "sort": "desc"
        }
      },
      "fieldConfig": {
        "defaults": {
          "unit": "reqps",
          "color": {
            "mode": "thresholds"
          },
          "custom": {
            "drawStyle": "line",
            "lineInterpolation": "linear",
            "barAlignment": 0,
            "lineWidth": 2,
            "fillOpacity": 10,
            "gradientMode": "none",
            "spanNulls": false,
            "showPoints": "never",
            "pointSize": 5,
            "stacking": {
              "mode": "none",
              "group": "A"
            },
            "axisPlacement": "auto",
            "axisLabel": "",
            "axisColorMode": "text",
            "scaleDistribution": {
              "type": "linear"
            },
            "axisCenteredZero": false,
            "hideFrom": {
              "tooltip": false,
              "viz": false,
              "legend": false
            },
            "thresholdsStyle": {
              "mode": "line"
            }
          },
          "thresholds": {
            "mode": "absolute",
            "steps": [
              {
                "color": "green",
                "value": null
              },
              {
                "color": "yellow",
                "value": 1
              },
              {
                "color": "red",
                "value": 5
              }
            ]
          }
        },
        "overrides": []
      },
      "description": "Completed versus aborted HTTP request rates."
    },
    {
      "id": 29,
      "type": "timeseries",
      "title": "Redis Ping ms from Capacity Snapshots (Loki)",
      "datasource": {
        "type": "loki",
        "uid": "loki"
      },
      "gridPos": {
        "h": 8,
        "w": 12,
        "x": 0,
        "y": 73
      },
      "targets": [
        {
          "refId": "A",
          "expr": "quantile_over_time(0.95, {job=~\".*\"} | json | kind=\"capacity_snapshot\" | unwrap capacity_redis_ping_ms [5m])",
          "legendFormat": "redis ping p95"
        }
      ],
      "options": {
        "legend": {
          "displayMode": "list",
          "placement": "bottom",
          "showLegend": true
        },
        "tooltip": {
          "mode": "multi",
          "sort": "desc"
        }
      },
      "fieldConfig": {
        "defaults": {
          "unit": "ms",
          "color": {
            "mode": "thresholds"
          },
          "custom": {
            "drawStyle": "line",
            "lineInterpolation": "linear",
            "barAlignment": 0,
            "lineWidth": 2,
            "fillOpacity": 10,
            "gradientMode": "none",
            "spanNulls": false,
            "showPoints": "never",
            "pointSize": 5,
            "stacking": {
              "mode": "none",
              "group": "A"
            },
            "axisPlacement": "auto",
            "axisLabel": "",
            "axisColorMode": "text",
            "scaleDistribution": {
              "type": "linear"
            },
            "axisCenteredZero": false,
            "hideFrom": {
              "tooltip": false,
              "viz": false,
              "legend": false
            },
            "thresholdsStyle": {
              "mode": "line"
            }
          },
          "thresholds": {
            "mode": "absolute",
            "steps": [
              {
                "color": "green",
                "value": null
              },
              {
                "color": "yellow",
                "value": 10
              },
              {
                "color": "red",
                "value": 25
              }
            ]
          }
        },
        "overrides": []
      },
      "description": "Log-based panel from structured capacity_snapshot events because redis_ping_ms is not a Prometheus metric."
    },
    {
      "id": 30,
      "type": "timeseries",
      "title": "DB Host iowait % (node exporter)",
      "datasource": {
        "type": "prometheus",
        "uid": "prometheus"
      },
      "gridPos": {
        "h": 8,
        "w": 12,
        "x": 12,
        "y": 73
      },
      "targets": [
        {
          "refId": "A",
          "expr": "100 * avg by (instance) (rate(node_cpu_seconds_total{job=\"db-node\",mode=\"iowait\"}[2m]))",
          "legendFormat": "{{instance}}"
        }
      ],
      "options": {
        "legend": {
          "displayMode": "list",
          "placement": "bottom",
          "showLegend": true
        },
        "tooltip": {
          "mode": "multi",
          "sort": "desc"
        }
      },
      "fieldConfig": {
        "defaults": {
          "unit": "percent",
          "color": {
            "mode": "thresholds"
          },
          "custom": {
            "drawStyle": "line",
            "lineInterpolation": "linear",
            "barAlignment": 0,
            "lineWidth": 2,
            "fillOpacity": 10,
            "gradientMode": "none",
            "spanNulls": false,
            "showPoints": "never",
            "pointSize": 5,
            "stacking": {
              "mode": "none",
              "group": "A"
            },
            "axisPlacement": "auto",
            "axisLabel": "",
            "axisColorMode": "text",
            "scaleDistribution": {
              "type": "linear"
            },
            "axisCenteredZero": false,
            "hideFrom": {
              "tooltip": false,
              "viz": false,
              "legend": false
            },
            "thresholdsStyle": {
              "mode": "line"
            }
          },
          "thresholds": {
            "mode": "absolute",
            "steps": [
              {
                "color": "green",
                "value": null
              },
              {
                "color": "yellow",
                "value": 10
              },
              {
                "color": "red",
                "value": 20
              }
            ]
          }
        },
        "overrides": []
      },
      "description": "Host-level DB disk iowait from node exporter if available."
    },
    {
      "id": 31,
      "type": "timeseries",
      "title": "WS Replay Query p95 / p99 by Result",
      "datasource": {
        "type": "prometheus",
        "uid": "prometheus"
      },
      "gridPos": {
        "h": 8,
        "w": 12,
        "x": 0,
        "y": 81
      },
      "targets": [
        {
          "expr": "histogram_quantile(0.95, sum by (le, result) (rate(ws_replay_query_duration_ms_bucket{job=\"chatapp-api\",vm=~\"$vm\",worker_port=~\"$worker\"}[2m])))",
          "legendFormat": "p95 {{result}}",
          "refId": "A"
        },
        {
          "expr": "histogram_quantile(0.99, sum by (le, result) (rate(ws_replay_query_duration_ms_bucket{job=\"chatapp-api\",vm=~\"$vm\",worker_port=~\"$worker\"}[2m])))",
          "legendFormat": "p99 {{result}}",
          "refId": "B"
        }
      ],
      "options": {
        "legend": {
          "displayMode": "list",
          "placement": "bottom",
          "showLegend": true
        },
        "tooltip": {
          "mode": "multi",
          "sort": "desc"
        }
      },
      "fieldConfig": {
        "defaults": {
          "unit": "reqps",
          "color": {
            "mode": "thresholds"
          },
          "custom": {
            "drawStyle": "line",
            "lineInterpolation": "linear",
            "barAlignment": 0,
            "lineWidth": 2,
            "fillOpacity": 10,
            "gradientMode": "none",
            "spanNulls": false,
            "showPoints": "never",
            "pointSize": 5,
            "stacking": {
              "mode": "none",
              "group": "A"
            },
            "axisPlacement": "auto",
            "axisLabel": "",
            "axisColorMode": "text",
            "scaleDistribution": {
              "type": "linear"
            },
            "axisCenteredZero": false,
            "hideFrom": {
              "tooltip": false,
              "viz": false,
              "legend": false
            },
            "thresholdsStyle": {
              "mode": "line"
            }
          },
          "thresholds": {
            "mode": "absolute",
            "steps": [
              {
                "color": "green",
                "value": null
              },
              {
                "color": "yellow",
                "value": 0.01
              },
              {
                "color": "red",
                "value": 0.1
              }
            ]
          }
        },
        "overrides": [
          {
            "matcher": {
              "id": "byName",
              "options": "timeout"
            },
            "properties": [
              {
                "id": "color",
                "value": {
                  "mode": "fixed",
                  "fixedColor": "red"
                }
              }
            ]
          },
          {
            "matcher": {
              "id": "byName",
              "options": "ok"
            },
            "properties": [
              {
                "id": "color",
                "value": {
                  "mode": "fixed",
                  "fixedColor": "green"
                }
              }
            ]
          }
        ]
      },
      "description": "Reconnect replay outcomes, especially timeout versus ok."
    },
    {
      "id": 32,
      "type": "timeseries",
      "title": "WS Replay Fail-Open Rate by Reason",
      "datasource": {
        "type": "prometheus",
        "uid": "prometheus"
      },
      "gridPos": {
        "h": 8,
        "w": 12,
        "x": 12,
        "y": 81
      },
      "targets": [
        {
          "expr": "sum by (reason) (rate(ws_replay_fail_open_total{job=\"chatapp-api\",vm=~\"$vm\",worker_port=~\"$worker\"}[2m]))",
          "legendFormat": "{{reason}}",
          "refId": "A"
        }
      ],
      "options": {
        "legend": {
          "displayMode": "list",
          "placement": "bottom",
          "showLegend": true
        },
        "tooltip": {
          "mode": "multi",
          "sort": "desc"
        }
      },
      "fieldConfig": {
        "defaults": {
          "unit": "reqps",
          "color": {
            "mode": "thresholds"
          },
          "custom": {
            "drawStyle": "line",
            "lineInterpolation": "linear",
            "barAlignment": 0,
            "lineWidth": 2,
            "fillOpacity": 10,
            "gradientMode": "none",
            "spanNulls": false,
            "showPoints": "never",
            "pointSize": 5,
            "stacking": {
              "mode": "none",
              "group": "A"
            },
            "axisPlacement": "auto",
            "axisLabel": "",
            "axisColorMode": "text",
            "scaleDistribution": {
              "type": "linear"
            },
            "axisCenteredZero": false,
            "hideFrom": {
              "tooltip": false,
              "viz": false,
              "legend": false
            },
            "thresholdsStyle": {
              "mode": "line"
            }
          },
          "thresholds": {
            "mode": "absolute",
            "steps": [
              {
                "color": "green",
                "value": null
              },
              {
                "color": "yellow",
                "value": 0.01
              },
              {
                "color": "red",
                "value": 0.1
              }
            ]
          }
        },
        "overrides": [
          {
            "matcher": {
              "id": "byName",
              "options": "timeout"
            },
            "properties": [
              {
                "id": "color",
                "value": {
                  "mode": "fixed",
                  "fixedColor": "red"
                }
              }
            ]
          },
          {
            "matcher": {
              "id": "byName",
              "options": "ok"
            },
            "properties": [
              {
                "id": "color",
                "value": {
                  "mode": "fixed",
                  "fixedColor": "green"
                }
              }
            ]
          }
        ]
      },
      "description": "Reconnect replay outcomes, especially timeout versus ok."
    },
    {
      "id": 33,
      "type": "timeseries",
      "title": "WS Replay Inflight by VM",
      "datasource": {
        "type": "prometheus",
        "uid": "prometheus"
      },
      "gridPos": {
        "h": 8,
        "w": 12,
        "x": 0,
        "y": 89
      },
      "targets": [
        {
          "expr": "sum by (vm) (chatapp_ws_replay_inflight{job=\"chatapp-api\",vm=~\"$vm\",worker_port=~\"$worker\"})",
          "legendFormat": "{{vm}}",
          "refId": "A"
        }
      ],
      "options": {
        "legend": {
          "displayMode": "list",
          "placement": "bottom",
          "showLegend": true
        },
        "tooltip": {
          "mode": "multi",
          "sort": "desc"
        }
      },
      "fieldConfig": {
        "defaults": {
          "unit": "reqps",
          "color": {
            "mode": "thresholds"
          },
          "custom": {
            "drawStyle": "line",
            "lineInterpolation": "linear",
            "barAlignment": 0,
            "lineWidth": 2,
            "fillOpacity": 10,
            "gradientMode": "none",
            "spanNulls": false,
            "showPoints": "never",
            "pointSize": 5,
            "stacking": {
              "mode": "none",
              "group": "A"
            },
            "axisPlacement": "auto",
            "axisLabel": "",
            "axisColorMode": "text",
            "scaleDistribution": {
              "type": "linear"
            },
            "axisCenteredZero": false,
            "hideFrom": {
              "tooltip": false,
              "viz": false,
              "legend": false
            },
            "thresholdsStyle": {
              "mode": "line"
            }
          },
          "thresholds": {
            "mode": "absolute",
            "steps": [
              {
                "color": "green",
                "value": null
              },
              {
                "color": "yellow",
                "value": 0.01
              },
              {
                "color": "red",
                "value": 0.1
              }
            ]
          }
        },
        "overrides": [
          {
            "matcher": {
              "id": "byName",
              "options": "timeout"
            },
            "properties": [
              {
                "id": "color",
                "value": {
                  "mode": "fixed",
                  "fixedColor": "red"
                }
              }
            ]
          },
          {
            "matcher": {
              "id": "byName",
              "options": "ok"
            },
            "properties": [
              {
                "id": "color",
                "value": {
                  "mode": "fixed",
                  "fixedColor": "green"
                }
              }
            ]
          }
        ]
      },
      "description": "Reconnect replay outcomes, especially timeout versus ok."
    },
    {
      "id": 34,
      "type": "timeseries",
      "title": "PG Pool Waiting by VM",
      "datasource": {
        "type": "prometheus",
        "uid": "prometheus"
      },
      "gridPos": {
        "h": 8,
        "w": 12,
        "x": 12,
        "y": 89
      },
      "targets": [
        {
          "expr": "max by (vm) (pg_pool_waiting{job=\"chatapp-api\",vm=~\"$vm\",worker_port=~\"$worker\"})",
          "legendFormat": "{{vm}}",
          "refId": "A"
        }
      ],
      "options": {
        "legend": {
          "displayMode": "list",
          "placement": "bottom",
          "showLegend": true
        },
        "tooltip": {
          "mode": "multi",
          "sort": "desc"
        }
      },
      "fieldConfig": {
        "defaults": {
          "unit": "reqps",
          "color": {
            "mode": "thresholds"
          },
          "custom": {
            "drawStyle": "line",
            "lineInterpolation": "linear",
            "barAlignment": 0,
            "lineWidth": 2,
            "fillOpacity": 10,
            "gradientMode": "none",
            "spanNulls": false,
            "showPoints": "never",
            "pointSize": 5,
            "stacking": {
              "mode": "none",
              "group": "A"
            },
            "axisPlacement": "auto",
            "axisLabel": "",
            "axisColorMode": "text",
            "scaleDistribution": {
              "type": "linear"
            },
            "axisCenteredZero": false,
            "hideFrom": {
              "tooltip": false,
              "viz": false,
              "legend": false
            },
            "thresholdsStyle": {
              "mode": "line"
            }
          },
          "thresholds": {
            "mode": "absolute",
            "steps": [
              {
                "color": "green",
                "value": null
              },
              {
                "color": "yellow",
                "value": 0.01
              },
              {
                "color": "red",
                "value": 0.1
              }
            ]
          }
        },
        "overrides": [
          {
            "matcher": {
              "id": "byName",
              "options": "timeout"
            },
            "properties": [
              {
                "id": "color",
                "value": {
                  "mode": "fixed",
                  "fixedColor": "red"
                }
              }
            ]
          },
          {
            "matcher": {
              "id": "byName",
              "options": "ok"
            },
            "properties": [
              {
                "id": "color",
                "value": {
                  "mode": "fixed",
                  "fixedColor": "green"
                }
              }
            ]
          }
        ]
      },
      "description": "Reconnect replay outcomes, especially timeout versus ok."
    }
  ],
  "refresh": "30s",
  "schemaVersion": 39,
  "style": "dark",
  "tags": [
    "chatapp",
    "sre",
    "failure-modes"
  ],
  "templating": {
    "list": [
      {
        "current": {
          "selected": true,
          "text": "All",
          "value": "$__all"
        },
        "datasource": {
          "type": "prometheus",
          "uid": "prometheus"
        },
        "definition": "label_values(up{job=\"chatapp-api\"}, vm)",
        "hide": 0,
        "includeAll": true,
        "allValue": ".*",
        "label": "VM",
        "multi": true,
        "name": "vm",
        "options": [],
        "query": {
          "query": "label_values(up{job=\"chatapp-api\"}, vm)",
          "refId": "PromVarVm"
        },
        "refresh": 2,
        "regex": "",
        "skipUrlSync": false,
        "sort": 1,
        "type": "query"
      },
      {
        "current": {
          "selected": true,
          "text": "All",
          "value": "$__all"
        },
        "datasource": {
          "type": "prometheus",
          "uid": "prometheus"
        },
        "definition": "label_values(up{job=\"chatapp-api\",vm=~\"$vm\"}, worker_port)",
        "hide": 0,
        "includeAll": true,
        "allValue": ".*",
        "label": "Worker port",
        "multi": true,
        "name": "worker",
        "options": [],
        "query": {
          "query": "label_values(up{job=\"chatapp-api\",vm=~\"$vm\"}, worker_port)",
          "refId": "PromVarWorker"
        },
        "refresh": 2,
        "regex": "",
        "skipUrlSync": false,
        "sort": 1,
        "type": "query"
      }
    ]
  },
  "time": {
    "from": "now-15m",
    "to": "now"
  },
  "timepicker": {},
  "timezone": "browser",
  "title": "ChatApp Failure Modes",
  "uid": "chatapp-failure-modes",
  "version": 1,
  "weekStart": ""
}
